agentcoach/__init__.py
agentcoach/canary.py
agentcoach/cli.py
agentcoach/config.py
agentcoach/contracts.py
agentcoach/judge.py
agentcoach/langgraph.py
agentcoach/models.py
agentcoach/repair.py
agentcoach/report.py
agentcoach/trace_ingest.py
agentcoach/detectors/__init__.py
agentcoach/detectors/base.py
agentcoach/detectors/consistency.py
agentcoach/detectors/grounding.py
agentcoach/detectors/loops.py
agentcoach/detectors/policy_tone.py
agentcoach/detectors/schema.py
agentcoach/detectors/state.py
agentcoach/detectors/tool_use.py
agentcoach-0.1.0.dist-info/licenses/LICENSE
agentcoach-0.1.0.dist-info/METADATA
agentcoach-0.1.0.dist-info/WHEEL
agentcoach-0.1.0.dist-info/entry_points.txt
agentcoach-0.1.0.dist-info/top_level.txt
agentcoach-0.1.0.dist-info/RECORD
