Metadata-Version: 2.4
Name: agentcoach
Version: 0.1.0
Summary: Agent quality analysis and repair SDK for OpenTelemetry traces
Author-email: AgentCoach Contributors <agentcoach@example.com>
Maintainer-email: AgentCoach Contributors <agentcoach@example.com>
License: MIT
Project-URL: Homepage, https://github.com/yourusername/agentcoach
Project-URL: Documentation, https://github.com/yourusername/agentcoach#readme
Project-URL: Repository, https://github.com/yourusername/agentcoach
Project-URL: Issues, https://github.com/yourusername/agentcoach/issues
Project-URL: Changelog, https://github.com/yourusername/agentcoach/blob/main/CHANGELOG.md
Keywords: agent,llm,quality,telemetry,opentelemetry,langgraph,ai,observability,testing,validation,repair,traces
Classifier: Development Status :: 3 - Alpha
Classifier: Intended Audience :: Developers
Classifier: License :: OSI Approved :: MIT License
Classifier: Operating System :: OS Independent
Classifier: Programming Language :: Python :: 3
Classifier: Programming Language :: Python :: 3.9
Classifier: Programming Language :: Python :: 3.10
Classifier: Programming Language :: Python :: 3.11
Classifier: Programming Language :: Python :: 3.12
Classifier: Topic :: Software Development :: Libraries :: Python Modules
Classifier: Topic :: Software Development :: Quality Assurance
Classifier: Topic :: Software Development :: Testing
Classifier: Topic :: Scientific/Engineering :: Artificial Intelligence
Requires-Python: >=3.9
License-File: LICENSE
Requires-Dist: click>=8.1.0
Requires-Dist: pydantic>=2.0.0
Requires-Dist: jinja2>=3.1.0
Requires-Dist: httpx>=0.27.0
Requires-Dist: pyyaml>=6.0
Requires-Dist: python-dotenv>=1.0.0
Requires-Dist: jsonschema>=4.0.0
Provides-Extra: dev
Requires-Dist: pytest>=7.4.0; extra == "dev"
Requires-Dist: pytest-asyncio>=0.21.0; extra == "dev"
Requires-Dist: ruff>=0.1.0; extra == "dev"
Requires-Dist: mypy>=1.7.0; extra == "dev"
Dynamic: license-file
